odoo/addons/product_margin_classification/README.rst
odoo/addons/product_margin_classification/__init__.py
odoo/addons/product_margin_classification/__manifest__.py
odoo/addons/product_margin_classification/data/decimal_precision.xml
odoo/addons/product_margin_classification/demo/product_margin_classification.xml
odoo/addons/product_margin_classification/demo/product_product.xml
odoo/addons/product_margin_classification/demo/res_groups.xml
odoo/addons/product_margin_classification/i18n/es.po
odoo/addons/product_margin_classification/i18n/fr.po
odoo/addons/product_margin_classification/i18n/it.po
odoo/addons/product_margin_classification/i18n/product_margin_classification.pot
odoo/addons/product_margin_classification/models/__init__.py
odoo/addons/product_margin_classification/models/product_margin_classification.py
odoo/addons/product_margin_classification/models/product_product.py
odoo/addons/product_margin_classification/models/product_template.py
odoo/addons/product_margin_classification/readme/CONFIGURE.rst
odoo/addons/product_margin_classification/readme/CONTRIBUTORS.rst
odoo/addons/product_margin_classification/readme/DESCRIPTION.rst
odoo/addons/product_margin_classification/readme/ROADMAP.rst
odoo/addons/product_margin_classification/readme/USAGE.rst
odoo/addons/product_margin_classification/security/ir.model.access.csv
odoo/addons/product_margin_classification/security/ir_rule.xml
odoo/addons/product_margin_classification/static/description/icon.png
odoo/addons/product_margin_classification/static/description/index.html
odoo/addons/product_margin_classification/static/description/margin_classification_form.png
odoo/addons/product_margin_classification/static/description/margin_classification_tree.png
odoo/addons/product_margin_classification/static/description/product_product_form.png
odoo/addons/product_margin_classification/static/description/product_product_tree_incorrect_price.png
odoo/addons/product_margin_classification/tests/__init__.py
odoo_addon_product_margin_classification-16.0.1.3.1.dist-info/METADATA
odoo_addon_product_margin_classification-16.0.1.3.1.dist-info/WHEEL
odoo_addon_product_margin_classification-16.0.1.3.1.dist-info/top_level.txt
odoo_addon_product_margin_classification-16.0.1.3.1.dist-info/RECORD
